scribbler/__init__.py
scribbler/apps.py
scribbler/conf.py
scribbler/forms.py
scribbler/models.py
scribbler/urls.py
scribbler/utils.py
scribbler/views.py
scribbler/locale/en/LC_MESSAGES/djangojs.po
scribbler/locale/fr/LC_MESSAGES/djangojs.po
scribbler/migrations/0001_initial.py
scribbler/migrations/__init__.py
scribbler/static/scribbler/css/scribbler.css
scribbler/static/scribbler/img/btn-close.png
scribbler/static/scribbler/js/djangohint.js
scribbler/static/scribbler/js/scribbler-editor.js
scribbler/static/scribbler/js/scribbler-main.js
scribbler/static/scribbler/js/scribbler-menu.js
scribbler/static/scribbler/js/scribbler-min.js
scribbler/static/scribbler/js/scribbler.js
scribbler/static/scribbler/js/plugins/themes.js
scribbler/static/scribbler/less/scribbler.less
scribbler/static/scribbler/libs/Backbone-LICENSE
scribbler/static/scribbler/libs/Browserify-LICENSE
scribbler/static/scribbler/libs/CodeMirror-LICENSE
scribbler/static/scribbler/libs/Underscore-LICENSE
scribbler/static/scribbler/libs/jQuery-LICENSE
scribbler/templates/scribbler/edit-form.html
scribbler/templates/scribbler/scribble-wrapper.html
scribbler/templatetags/__init__.py
scribbler/templatetags/scribbler_tags.py
scribbler/tests/__init__.py
scribbler/tests/base.py
scribbler/tests/jinja2.py
scribbler/tests/test_templatetags.py
scribbler/tests/test_utils.py
scribbler/tests/test_views.py
scribbler/tests/urls.py
scribbler/tests/migrations/__init__.py
scribbler/tests/qunit/editor-test.js
scribbler/tests/qunit/index.html
scribbler/tests/qunit/main.js
scribbler/tests/qunit/menu-test.js
scribbler/tests/qunit/runner.js
scribbler/tests/qunit/template.html
django_scribbler-1.2.0.dist-info/AUTHORS
django_scribbler-1.2.0.dist-info/LICENSE
django_scribbler-1.2.0.dist-info/METADATA
django_scribbler-1.2.0.dist-info/WHEEL
django_scribbler-1.2.0.dist-info/top_level.txt
django_scribbler-1.2.0.dist-info/RECORD
